bitmicro/__init__.py
bitmicro/core.py
bitmicro-1.0.1.dist-info/LICENSE
bitmicro-1.0.1.dist-info/METADATA
bitmicro-1.0.1.dist-info/WHEEL
bitmicro-1.0.1.dist-info/top_level.txt
bitmicro-1.0.1.dist-info/RECORD
