Metadata-Version: 2.1
Name: bitmicro
Version: 1.0.1
Summary: MicroBitcoin (MBC) Python library – Bitcash-style wallet & network API
Home-page: https://github.com/COXKPER/bitmicro
Author: Neoncorp
Author-email: Neoncorp <snurlaelah163@gmail.com>
License: GNU GENERAL PUBLIC LICENSE
Project-URL: Homepage, https://github.com/COXKPER/bitmicro
Classifier: Programming Language :: Python :: 3
Classifier: License :: OSI Approved :: GNU General Public License v3 (GPLv3)
Classifier: Operating System :: OS Independent
Requires-Python: >=3.7
License-File: LICENSE
Requires-Dist: base58
Requires-Dist: ecdsa
Requires-Dist: requests
